whitebox_tempest_plugin/README.rst
whitebox_tempest_plugin/__init__.py
whitebox_tempest_plugin/config.py
whitebox_tempest_plugin/exceptions.py
whitebox_tempest_plugin/hardware.py
whitebox_tempest_plugin/plugin.py
whitebox_tempest_plugin/utils.py
whitebox_tempest_plugin/api/__init__.py
whitebox_tempest_plugin/api/compute/__init__.py
whitebox_tempest_plugin/api/compute/base.py
whitebox_tempest_plugin/api/compute/numa_helper.py
whitebox_tempest_plugin/api/compute/test_compute_id.py
whitebox_tempest_plugin/api/compute/test_console_encryption.py
whitebox_tempest_plugin/api/compute/test_cpu_model_extra_flags.py
whitebox_tempest_plugin/api/compute/test_cpu_pinning.py
whitebox_tempest_plugin/api/compute/test_cpu_state_mgmt.py
whitebox_tempest_plugin/api/compute/test_default_hyperv_enlightenments.py
whitebox_tempest_plugin/api/compute/test_file_backed_memory.py
whitebox_tempest_plugin/api/compute/test_hugepages.py
whitebox_tempest_plugin/api/compute/test_hw_video_type.py
whitebox_tempest_plugin/api/compute/test_live_migration.py
whitebox_tempest_plugin/api/compute/test_multiqueue.py
whitebox_tempest_plugin/api/compute/test_nvdimm.py
whitebox_tempest_plugin/api/compute/test_pointer_device_type.py
whitebox_tempest_plugin/api/compute/test_rbd_direct_download.py
whitebox_tempest_plugin/api/compute/test_rx_tx_queue_size.py
whitebox_tempest_plugin/api/compute/test_server_evacuation.py
whitebox_tempest_plugin/api/compute/test_sriov.py
whitebox_tempest_plugin/api/compute/test_uefi.py
whitebox_tempest_plugin/api/compute/test_validate_selinux_labels.py
whitebox_tempest_plugin/api/compute/test_vdpa.py
whitebox_tempest_plugin/api/compute/test_vgpu.py
whitebox_tempest_plugin/api/compute/test_viommu_devices.py
whitebox_tempest_plugin/api/compute/test_virtio_rng.py
whitebox_tempest_plugin/api/compute/test_virtio_scsi_attach.py
whitebox_tempest_plugin/api/compute/test_volume_encryption.py
whitebox_tempest_plugin/api/compute/test_volume_negative.py
whitebox_tempest_plugin-0.1.0.dist-info/AUTHORS
whitebox_tempest_plugin-0.1.0.dist-info/LICENSE
whitebox_tempest_plugin-0.1.0.dist-info/METADATA
whitebox_tempest_plugin-0.1.0.dist-info/WHEEL
whitebox_tempest_plugin-0.1.0.dist-info/entry_points.txt
whitebox_tempest_plugin-0.1.0.dist-info/pbr.json
whitebox_tempest_plugin-0.1.0.dist-info/top_level.txt
whitebox_tempest_plugin-0.1.0.dist-info/RECORD
