Metadata-Version: 2.1
Name: whitebox-tempest-plugin
Version: 0.1.0
Summary: Tempest plugin for whitebox testing. For testing things not exposed through the REST APIs.
Home-page: https://opendev.org/openstack/whitebox-tempest-plugin
Author: OpenStack
Author-email: openstack-discuss@lists.openstack.org
Classifier: Intended Audience :: Information Technology
Classifier: Intended Audience :: System Administrators
Classifier: Intended Audience :: Developers
Classifier: License :: OSI Approved :: Apache Software License
Classifier: Operating System :: POSIX :: Linux
Classifier: Programming Language :: Python
Classifier: Programming Language :: Python :: 3
Classifier: Programming Language :: Python :: 3.6
Classifier: Programming Language :: Python :: 3.8
Classifier: Programming Language :: Python :: 3.9
Classifier: Programming Language :: Python :: 3.10
License-File: LICENSE
License-File: AUTHORS
Requires-Dist: setuptools >=17.1
Requires-Dist: crudini >=0.9.3
Requires-Dist: paramiko >=2.7.0
Requires-Dist: pymysql
Requires-Dist: ddt >=1.6.0
Requires-Dist: barbican-tempest-plugin <=1.6.0 ; (python_version<='3.6')
Requires-Dist: iniparse >=0.4 ; (python_version=='2.7')
Requires-Dist: sshtunnel <=0.1.3 ; (python_version=='2.7')
Requires-Dist: cryptography <3.3 ; (python_version=='3.6')
Requires-Dist: bcrypt <3.2 ; (python_version=='3.6')
Requires-Dist: barbican-tempest-plugin ; (python_version>'3.6')
Requires-Dist: iniparse >=0.5 ; (python_version>='3.6')
Requires-Dist: sshtunnel ; (python_version>='3.6')
